README.md
setup.py
src/vdk/plugin/huggingface/ingest.py
src/vdk/plugin/huggingface/plugin_entry.py
src/vdk_huggingface.egg-info/PKG-INFO
src/vdk_huggingface.egg-info/SOURCES.txt
src/vdk_huggingface.egg-info/dependency_links.txt
src/vdk_huggingface.egg-info/entry_points.txt
src/vdk_huggingface.egg-info/requires.txt
src/vdk_huggingface.egg-info/top_level.txt
tests/test_huggingface_plugin.py