Metadata-Version: 2.1
Name: vdk-huggingface
Version: 0.1.1058840798
Summary: Integrate VDK with Huggingface as both data source and target
Home-page: https://github.com/vmware/versatile-data-kit
Project-URL: Documentation, https://github.com/vmware/versatile-data-kit/tree/main/projects/vdk-plugins/vdk-huggingface
Project-URL: Source Code, https://github.com/vmware/versatile-data-kit/tree/main/projects/vdk-plugins/vdk-huggingface
Project-URL: Bug Tracker, https://github.com/vmware/versatile-data-kit/issues/new/choose
Classifier: Development Status :: 2 - Pre-Alpha
Classifier: License :: OSI Approved :: Apache Software License
Classifier: Programming Language :: Python :: 3.7
Classifier: Programming Language :: Python :: 3.8
Classifier: Programming Language :: Python :: 3.9
Classifier: Programming Language :: Python :: 3.10
Classifier: Programming Language :: Python :: 3.11
Requires-Dist: vdk-core
Requires-Dist: huggingface-hub
